[
  {
    "symbol": "AFL",
    "price": 68.38,
    "beta": 0.935915,
    "volAvg": 2339619,
    "mktCap": 41317042807,
    "lastDiv": 1.68,
    "range": "53.04-74.02",
    "changes": -0.12,
    "companyName": "Aflac Incorporated",
    "currency": "USD",
    "cik": "0000004977",
    "isin": "US0010551028",
    "cusip": "001055102",
    "exchange": "New York Stock Exchange",
    "exchangeShortName": "NYSE",
    "industry": "Insurance—Life",
    "website": "https://www.aflac.com",
    "description": "Aflac Incorporated, through its subsidiaries, provides supplemental health and life insurance products. It operates through two segments, Aflac Japan and Aflac U.S. The Aflac Japan segment offers cancer, medical, nursing care income support, GIFT, and whole and term life insurance products, as well as WAYS and child endowment plans under saving type insurance products in Japan. The Aflac U.S. segment provides cancer, accident, short-term disability, critical illness, hospital indemnity, dental, vision, long-term care and disability, and term and whole life insurance products in the United States. It sells its products through sales associates, brokers, independent corporate agencies, individual agencies, and affiliated corporate agencies. The company was founded in 1955 and is based in Columbus, Georgia.",
    "ceo": "Mr. Daniel Paul Amos",
    "sector": "Financial Services",
    "country": "US",
    "fullTimeEmployees": "12882",
    "phone": "706 323 3431",
    "address": "1932 Wynnton Road",
    "city": "Columbus",
    "state": "GA",
    "zip": "31999",
    "dcfDiff": 5.51258,
    "dcf": 78.4226,
    "image": "https://financialmodelingprep.com/image-stock/AFL.png",
    "ipoDate": "1980-03-17",
    "defaultImage": false,
    "isEtf": false,
    "isActivelyTrading": true,
    "isAdr": false,
    "isFund": false
  }
]