[
  {
    "symbol": "ATDRY",
    "price": 1.86,
    "beta": 0.611877,
    "volAvg": 128040,
    "mktCap": 6787512238,
    "lastDiv": 0.03,
    "range": "1.3-2.02",
    "changes": -0.02,
    "companyName": "Auto Trader Group plc",
    "currency": "USD",
    "cik": null,
    "isin": "US05277E1047",
    "cusip": null,
    "exchange": "Other OTC",
    "exchangeShortName": "PNK",
    "industry": "Internet Content & Information",
    "website": "https://www.autotrader.co.uk",
    "description": "Auto Trader Group plc operates in the digital automotive marketplace in the United Kingdom and Ireland. The company provides vehicle advertisement on its websites for private sellers, as well as insurance and loan financing products to consumers; and display advertising on its websites for manufacturers and their advertising agencies. It offers its products to retailers, home traders, and logistics firms. Auto Trader Group plc was founded in 1977 and is headquartered in Manchester, the United Kingdom.",
    "ceo": "Mr. Nathan  Coe",
    "sector": "Communication Services",
    "country": "GB",
    "fullTimeEmployees": "1226",
    "phone": "44 34 5111 0006",
    "address": "1 Tony Wilson Place",
    "city": "Manchester",
    "state": null,
    "zip": "M15 4FN",
    "dcfDiff": null,
    "dcf": 0,
    "image": "https://financialmodelingprep.com/image-stock/ATDRY.png",
    "ipoDate": "2015-08-11",
    "defaultImage": false,
    "isEtf": false,
    "isActivelyTrading": true,
    "isAdr": false,
    "isFund": false
  }
]