[
  {
    "symbol": "AVY",
    "price": 165.47,
    "beta": 0.965845,
    "volAvg": 575969,
    "mktCap": 13421106230,
    "lastDiv": 3.24,
    "range": "157.28-204.37",
    "changes": -4.93,
    "companyName": "Avery Dennison Corporation",
    "currency": "USD",
    "cik": "0000008818",
    "isin": "US0536111091",
    "cusip": "053611109",
    "exchange": "New York Stock Exchange",
    "exchangeShortName": "NYSE",
    "industry": "Business Equipment & Supplies",
    "website": "https://www.averydennison.com",
    "description": "Avery Dennison Corporation manufactures and markets pressure-sensitive materials and products in the United States, Europe, Asia, Latin America, and internationally. The company's Label and Graphic Materials segment offers pressure-sensitive label and packaging materials; and graphics and reflective products under the Fasson, JAC, Avery Dennison, and Mactac brands, as well as durable cast and reflective films. It provides its products to the home and personal care, beer and beverage, durables, pharmaceutical, wine and spirits, and food market segments; architectural, commercial sign, digital printing, and other related market segments; construction, automotive, and fleet transportation market segments, as well as traffic and safety applications; and sign shops, commercial printers, and designers. The company's Retail Branding and Information Solutions segment designs, manufactures, and sells brand embellishments, graphic tickets, tags and labels, and sustainable packaging solutions, as well as offers creative services; radio-frequency identification products; visibility and loss prevention solutions; price ticketing and marking solutions; care, content, and country of origin compliance solutions; and brand protection and security solutions. It serves retailers, brand owners, apparel manufacturers, distributors, and industrial customers. The company's Industrial and Healthcare Materials segment offers tapes; pressure-sensitive adhesive based materials and converted products; medical fasteners; and performance polymers under the Fasson, Avery Dennison, and Yongle brands. It serves automotive, electronics, building and construction, general industrial, personal care, and medical markets. The company was formerly known as Avery International Corporation and changed its name to Avery Dennison Corporation in 1990. Avery Dennison Corporation was founded in 1935 and is headquartered in Glendale, California.",
    "ceo": "Mr. Mitchell R. Butier",
    "sector": "Industrials",
    "country": "US",
    "fullTimeEmployees": "35660",
    "phone": "626 304 2000",
    "address": "207 Goode Avenue",
    "city": "Glendale",
    "state": "CA",
    "zip": "91203",
    "dcfDiff": 3.66461,
    "dcf": 191.115,
    "image": "https://financialmodelingprep.com/image-stock/AVY.png",
    "ipoDate": "1973-02-21",
    "defaultImage": false,
    "isEtf": false,
    "isActivelyTrading": true,
    "isAdr": false,
    "isFund": false
  }
]