[
  {
    "symbol": "MAR",
    "price": 177.66,
    "beta": 1.583098,
    "volAvg": 1693008,
    "mktCap": 53893868797,
    "lastDiv": 2.08,
    "range": "133.07-183.33",
    "changes": 0.35,
    "companyName": "Marriott International, Inc.",
    "currency": "USD",
    "cik": "0001048286",
    "isin": "US5719032022",
    "cusip": "571903202",
    "exchange": "NASDAQ Global Select",
    "exchangeShortName": "NASDAQ",
    "industry": "Lodging",
    "website": "https://www.marriott.com",
    "description": "Marriott International, Inc. operates, franchises, and licenses hotel, residential, and timeshare properties worldwide. The company operates through U.S. and Canada, and International segments. It operates its properties under the JW Marriott, The Ritz-Carlton, Ritz-Carlton Reserve, W Hotels, The Luxury Collection, St. Regis, EDITION, Bulgari, Marriott Hotels, Sheraton, Delta Hotels, Marriott Executive Apartments, Marriott Vacation Club, Westin, Renaissance, Le Méridien, Autograph Collection, Gaylord Hotels, Tribute Portfolio, Design Hotels, Courtyard, Residence Inn, Fairfield by Marriott, SpringHill Suites, Four Points, TownePlace Suites, Aloft, AC Hotels by Marriott, Protea Hotels, Element, and Moxy brand names. As of February 15, 2022, it operated approximately 7,989 properties under 30 hotel brands in 139 countries and territories. Marriott International, Inc. was founded in 1927 and is headquartered in Bethesda, Maryland.",
    "ceo": "Mr. Anthony G. Capuano Jr.",
    "sector": "Consumer Cyclical",
    "country": "US",
    "fullTimeEmployees": "377000",
    "phone": "301 380 3000",
    "address": "10400 Fernwood Road",
    "city": "Bethesda",
    "state": "MD",
    "zip": "20817",
    "dcfDiff": 9.52437,
    "dcf": 164.806,
    "image": "https://financialmodelingprep.com/image-stock/MAR.png",
    "ipoDate": "1998-03-23",
    "defaultImage": false,
    "isEtf": false,
    "isActivelyTrading": true,
    "isAdr": false,
    "isFund": false
  }
]