[
  {
    "symbol": "NEM",
    "price": 41.18,
    "beta": 0.348591,
    "volAvg": 8260383,
    "mktCap": 32727022909,
    "lastDiv": 1.6,
    "range": "37.45-63.93",
    "changes": -1.28,
    "companyName": "Newmont Corporation",
    "currency": "USD",
    "cik": "0001164727",
    "isin": "US6516391066",
    "cusip": "651639106",
    "exchange": "New York Stock Exchange",
    "exchangeShortName": "NYSE",
    "industry": "Gold",
    "website": "https://www.newmont.com",
    "description": "Newmont Corporation engages in the production and exploration of gold. It also explores for copper, silver, zinc, and lead. The company has operations and/or assets in the United States, Canada, Mexico, Dominican Republic, Peru, Suriname, Argentina, Chile, Australia, and Ghana. As of December 31, 2021, it had proven and probable gold reserves of 92.8 million ounces and land position of 62,800 square kilometers. The company was founded in 1916 and is headquartered in Denver, Colorado.",
    "ceo": "Mr. Thomas Ronald Palmer",
    "sector": "Basic Materials",
    "country": "US",
    "fullTimeEmployees": "14600",
    "phone": "303 863 7414",
    "address": "6900 East Layton Avenue",
    "city": "Denver",
    "state": "CO",
    "zip": "80237",
    "dcfDiff": 2.08,
    "dcf": 51.24,
    "image": "https://financialmodelingprep.com/image-stock/NEM.png",
    "ipoDate": "1980-03-17",
    "defaultImage": false,
    "isEtf": false,
    "isActivelyTrading": true,
    "isAdr": false,
    "isFund": false
  }
]