[
  {
    "symbol": "NTCO",
    "price": 6.9,
    "beta": 1.053881,
    "volAvg": 1192077,
    "mktCap": 4737671155,
    "lastDiv": 0.05,
    "range": "3.61-7.41",
    "changes": -0.29,
    "companyName": "Natura &Co Holding S.A.",
    "currency": "USD",
    "cik": "0001776967",
    "isin": "US63884N1081",
    "cusip": "63884N108",
    "exchange": "New York Stock Exchange",
    "exchangeShortName": "NYSE",
    "industry": "Household & Personal Products",
    "website": "https://ri.naturaeco.com/en",
    "description": "Natura &Co Holding S.A. develops, manufactures, distributes, and sells cosmetics, fragrances, and personal hygiene products. The company's products portfolio includes body care, face care, makeup, soaps, hair care, deodorants, oils, and other products, as well as deodorants, men's grooming, and sun protection products. It markets its products under the Natura, Aesop, Avon, and The Body Shop brands through signature and department stores, e-commerce, direct selling, business-to-business, franchises, physical stores, and retail markets primarily in Asia, North America, South America, Europe, the Middle East, Africa, and Oceania. Natura &Co Holding S.A. was founded in 1969 and is headquartered in São Paulo, Brazil.",
    "ceo": "Mr. Joao Paulo Brotto Gonçalves Ferreira",
    "sector": "Consumer Defensive",
    "country": "BR",
    "fullTimeEmployees": "18585",
    "phone": "55 11 4389 7881",
    "address": "Avenida Alexandre Colares",
    "city": "São Paulo",
    "state": "SP",
    "zip": "05106-000",
    "dcfDiff": null,
    "dcf": 0,
    "image": "https://financialmodelingprep.com/image-stock/NTCO.png",
    "ipoDate": "2020-01-06",
    "defaultImage": true,
    "isEtf": false,
    "isActivelyTrading": true,
    "isAdr": true,
    "isFund": false
  }
]