[
  {
    "symbol": "NVO",
    "price": 156.79,
    "beta": 0.319923,
    "volAvg": 1362259,
    "mktCap": 351521594540,
    "lastDiv": 1.76,
    "range": "95.02-172.97",
    "changes": 0.81,
    "companyName": "Novo Nordisk A/S",
    "currency": "USD",
    "cik": "0000353278",
    "isin": "US6701002056",
    "cusip": "670100205",
    "exchange": "New York Stock Exchange",
    "exchangeShortName": "NYSE",
    "industry": "Biotechnology",
    "website": "https://www.novonordisk.com",
    "description": "Novo Nordisk A/S, a healthcare company, engages in the research, development, manufacture, and marketing of pharmaceutical products worldwide. It operates in two segments, Diabetes and Obesity care, and Biopharm. The Diabetes and Obesity care segment provides products in the areas of insulins, GLP-1 and related delivery systems, oral antidiabetic products, obesity, and other chronic diseases. The Biopharmaceuticals segment offers products in the areas of haemophilia, growth disorders, and hormone replacement therapy. The company collaboration agreements with Gilead Sciences, Inc. Novo Nordisk A/S also has a research collaboration with Lumen Bioscience, Inc. to explore strategies for delivering oral biologics for cardiometabolic disease. The company was founded in 1923 and is headquartered in Bagsvaerd, Denmark.",
    "ceo": "Mr. Lars Fruergaard Jorgensen",
    "sector": "Healthcare",
    "country": "DK",
    "fullTimeEmployees": "57089",
    "phone": "45 44 44 88 88",
    "address": "Novo Allé 1",
    "city": "Bagsvaerd",
    "state": null,
    "zip": "2880",
    "dcfDiff": 20.0868,
    "dcf": 118.003,
    "image": "https://financialmodelingprep.com/image-stock/NVO.png",
    "ipoDate": "1981-04-30",
    "defaultImage": false,
    "isEtf": false,
    "isActivelyTrading": true,
    "isAdr": true,
    "isFund": false
  }
]