[
  {
    "symbol": "SGPYY",
    "price": 46.26,
    "beta": 0.534865,
    "volAvg": 11158,
    "mktCap": 11853338210,
    "lastDiv": 0.91,
    "range": "29.91-46.46",
    "changes": 1.68,
    "companyName": "The Sage Group plc",
    "currency": "USD",
    "cik": null,
    "isin": "US78663S2014",
    "cusip": null,
    "exchange": "Other OTC",
    "exchangeShortName": "PNK",
    "industry": "Software—Application",
    "website": "https://www.sage.com",
    "description": "The Sage Group plc, together with its subsidiaries, provides technology solutions and services for small and medium businesses in North America, Northern Europe, and internationally. It offers cloud native solutions, such as Sage Intacct, a cloud accounting software products and financial management solutions; Sage People, a cloud HR and people management solution; Sage Accounting, a solution for small businesses, accountants, and bookkeepers to remotely manage customer data, accounts, and people; Sage Payroll, a cloud-based payroll solution; and Sage HR, a HR management solution. The company also provides cloud connected and hybrid solutions, including Sage X3, a business management solution; and Sage 50cloud and Sage 200cloud that provides a range of cloud connected accounting solutions. The company was founded in 1981 and is based in Newcastle upon Tyne, the United Kingdom.",
    "ceo": "Mr. Stephen  Hare ACA, B.A., B.Com",
    "sector": "Technology",
    "country": "GB",
    "fullTimeEmployees": "11574",
    "phone": null,
    "address": "C23 5 & 6 Cobalt Park Way",
    "city": "Newcastle upon Tyne",
    "state": null,
    "zip": "NE28 9EJ",
    "dcfDiff": null,
    "dcf": 0,
    "image": "https://financialmodelingprep.com/image-stock/SGPYY.png",
    "ipoDate": "2007-10-04",
    "defaultImage": false,
    "isEtf": false,
    "isActivelyTrading": true,
    "isAdr": false,
    "isFund": false
  }
]